image_combination/__init__.py
image_combination/teste.py
image_combination/processing/__init__.py
image_combination/processing/combination.py
image_combination/processing/transformation.py
image_combination/utils/__init__.py
image_combination/utils/io.py
image_combination/utils/plot.py
image_combination-0.0.1.dist-info/METADATA
image_combination-0.0.1.dist-info/WHEEL
image_combination-0.0.1.dist-info/top_level.txt
image_combination-0.0.1.dist-info/RECORD
