Metadata-Version: 2.1
Name: image-combination
Version: 0.0.1
Summary: UNKNOWN
Home-page: https://github.com/EvertonVaz/bootcamps/tree/main/cognizant/IMAGE_PROCESSING-PACKAGE
Author: Everton Vaz
Author-email: etovaz.web@gmail.com
License: UNKNOWN
Platform: UNKNOWN
